{
  "parent": "ragium:tier1/ragi_alloy_plate",
  "criteria": {
    "has_items": {
      "conditions": {
        "items": [
          {
            "items": "ragium:primitive_hull"
          }
        ]
      },
      "trigger": "minecraft:inventory_changed"
    }
  },
  "display": {
    "description": {
      "translate": "advancement.ragium.tier1.ragi_alloy_hull.description"
    },
    "icon": {
      "count": 1,
      "id": "ragium:primitive_hull"
    },
    "title": {
      "translate": "advancement.ragium.tier1.ragi_alloy_hull"
    }
  },
  "requirements": [
    [
      "has_items"
    ]
  ],
  "sends_telemetry_event": true
}